{
  "nodes": [
    {
      "id": "dish:xiangla-xiaochao-huangniurou",
      "type": "service",
      "name": "香辣小炒黄牛肉",
      "summary": "湘遇川味 川湘荟萃·香辣小炒黄牛肉",
      "tags": [
        "湘遇川味",
        "川湘菜",
        "香辣小炒黄牛肉"
      ],
      "complexity": "moderate",
      "metadata": {
        "dishProfile": {
          "name": "香辣小炒黄牛肉",
          "cuisineCategory": "川湘菜",
          "coreSellingPoint": "精选湘西散养黄牛后腿肉，猛火快炒锁住肉汁，湘式剁椒与郫县豆瓣双辣合璧，粤菜馆里最地道的湘味小炒",
          "coreIngredients": "黄牛后腿肉、湖南剁椒、郫县豆瓣酱、青红椒圈、蒜苗、生姜（湖南湘西散养黄牛、郫县陈年豆瓣、湖南本地剁椒）",
          "cookingTechnique": "[高] 逆纹切薄片→料酒生抽码味→猛火宽油滑散→下剁椒豆瓣爆香→青红椒蒜苗翻炒→锅边烹酒收汁（鲜红牛肉片→码味后略带酱色→滑油后表面变白微卷→爆炒后挂满红油酱褐→收汁后油亮焦香）",
          "tasteProfile": "麻辣鲜香、肉嫩多汁、辣而不燥、后味回甘，配:郫县豆瓣酱、生抽、料酒、白糖少许提鲜",
          "closeupFeature": "牛肉片薄而完整，表面挂满红油酱汁，边缘微卷泛焦香色，剁椒碎粒嵌于肉纹之间，青红椒圈点缀其间，油光闪烁",
          "mediumFeature": "铁锅中牛肉与辣椒翻飞，锅气蒸腾，肉片在烈焰中跳跃，蒜苗青翠与红油形成鲜明色彩对比，镬气十足",
          "fullFeature": "白瓷盘中堆叠如山的香辣牛肉，红黄绿三色交映，热气升腾，配以竹制筷架与青瓷小碗，餐桌氛围热烈",
          "colorTexture": "酱红底色配翠绿蒜苗，牛肉深褐带焦边，剁椒鲜红欲滴，油亮润泽",
          "cameraSetup": "RED V-Raptor + Sigma Cine Classic",
          "colorTone": "镬气橙红",
          "bestAngle": "镬气翻腾",
          "thumbnailFrame": "香辣小炒黄牛肉，镬气翻腾瞬间，镬气橙红色调，极浅景深，背景全暗，左上45度侧光，牛肉片薄而完整，表面挂满红油酱汁，边缘微，蒸汽/油光粒子，9:16竖屏构图，极致特写，无人物出镜，无文字叠加"
        }
      }
    },
    {
      "id": "dish:xiangla-yangpai",
      "type": "service",
      "name": "香辣羊排",
      "summary": "湘遇川味 川湘荟萃·香辣羊排",
      "tags": [
        "湘遇川味",
        "川湘菜",
        "香辣羊排"
      ],
      "complexity": "moderate",
      "metadata": {
        "dishProfile": {
          "name": "香辣羊排",
          "cuisineCategory": "川湘菜",
          "coreSellingPoint": "内蒙古羔羊肋排先卤后炒，骨肉分离不散，川式干辣与粤式卤香交融，外焦里嫩一口脱骨",
          "coreIngredients": "羔羊肋排、干辣椒节、花椒、孜然粉、白芝麻、洋葱丝、香菜（内蒙古锡林郭勒6月龄羔羊、四川汉源花椒、新疆孜然）",
          "cookingTechnique": "[高] 羊排焯水去膻→秘制卤水慢炖90分钟→捞出沥干→宽油炸至金黄酥脆→锅留底油爆香干辣椒花椒→下羊排翻炒撒孜然→出锅撒白芝麻香菜（鲜红羊排→焯水后灰白→卤制后酱褐软烂→油炸后金黄酥脆→翻炒后挂满辣椒孜然粒）",
          "tasteProfile": "外酥里嫩、麻辣干香、孜然浓烈、卤味回甘，配:秘制卤水、干辣椒节、孜然粉、白芝麻",
          "closeupFeature": "羊排骨肉分明，肉面金黄酥脆带焦斑，辣椒节与花椒粒粘附其上，孜然颗粒均匀散落，白芝麻点缀，肉质纹理清晰可见",
          "mediumFeature": "铁锅中羊排翻滚，干辣椒与花椒在油中跳跃，孜然粉撒下瞬间香气弥漫，羊排表面滋滋作响冒油泡",
          "fullFeature": "长方形黑石板上整齐排列香辣羊排，干辣椒与香菜装饰两侧，配以柠檬角与蘸料碟，粗犷中见精致",
          "colorTexture": "金黄焦脆外皮，深褐卤色肉面，红干辣椒与绿香菜交映，油润干香",
          "cameraSetup": "Canon R5 C + RF 100mm f/2.8L Macro IS",
          "colorTone": "烧腊暖金",
          "bestAngle": "皮肉切面",
          "thumbnailFrame": "香辣羊排，皮肉切面特写，烧腊暖金色调，极浅景深，背景全暗，左上45度侧光，羊排骨肉分明，肉面金黄酥脆带焦斑，辣椒节，蒸汽/油光粒子，9:16竖屏构图，极致特写，无人物出镜，无文字叠加"
        }
      }
    },
    {
      "id": "dish:jiaxiang-xiaochao-rou",
      "type": "service",
      "name": "家乡小炒肉",
      "summary": "湘遇川味 川湘荟萃·家乡小炒肉",
      "tags": [
        "湘遇川味",
        "川湘菜",
        "家乡小炒肉"
      ],
      "complexity": "moderate",
      "metadata": {
        "dishProfile": {
          "name": "家乡小炒肉",
          "cuisineCategory": "川湘菜",
          "coreSellingPoint": "湖南土猪五花肉与螺丝椒的经典搭配，肥瘦相间煸出油脂，青椒断生脆嫩，最下饭的湘菜灵魂",
          "coreIngredients": "湖南土猪五花肉、螺丝椒（青尖椒）、豆豉、蒜子、生抽、老抽（湖南宁乡土猪、湖南本地螺丝椒、浏阳豆豉）",
          "cookingTechnique": "[中] 五花肉切薄片→干锅煸出油脂→肉片微焦拨一边→下螺丝椒大火翻炒→加豆豉蒜子爆香→烹入生抽老抽翻匀→大火收汁出锅（粉红五花肉→干煸后出油微焦→肥肉变透明→螺丝椒由翠绿变虎皮斑→翻炒后肉片裹酱色→收汁后油亮入味）",
          "tasteProfile": "咸香微辣、肥而不腻、椒香脆嫩、豆豉提鲜，配:生抽、老抽、豆豉、蒜子",
          "closeupFeature": "五花肉片边缘微卷焦黄，肥肉部分透明泛油光，瘦肉深褐入味，螺丝椒翠绿带虎皮焦斑，豆豉颗粒散落其间",
          "mediumFeature": "铁锅中五花肉滋滋冒油，螺丝椒在肉油中翻炒变软，豆豉与蒜子爆香，锅边沿有微微焦色，油光闪动",
          "fullFeature": "青花瓷盘中五花肉与青椒交织堆叠，油润发亮，热气蒸腾，配白米饭与青花小碗，质朴家常气息",
          "colorTexture": "酱褐肉片配翠绿青椒，肥肉透明油亮，豆豉乌黑点缀，整体油润光泽",
          "cameraSetup": "RED V-Raptor + Sigma Cine Classic",
          "colorTone": "镬气橙红",
          "bestAngle": "镬气翻腾",
          "thumbnailFrame": "家乡小炒肉，镬气翻腾瞬间，镬气橙红色调，极浅景深，背景全暗，左上45度侧光，五花肉片边缘微卷焦黄，肥肉部分透明泛油光，蒸汽/油光粒子，9:16竖屏构图，极致特写，无人物出镜，无文字叠加"
        }
      }
    },
    {
      "id": "dish:feiteng-huangniurou",
      "type": "service",
      "name": "沸腾黄牛肉",
      "summary": "湘遇川味 川湘荟萃·沸腾黄牛肉",
      "tags": [
        "湘遇川味",
        "川湘菜",
        "沸腾黄牛肉"
      ],
      "complexity": "moderate",
      "metadata": {
        "dishProfile": {
          "name": "沸腾黄牛肉",
          "cuisineCategory": "川湘菜",
          "coreSellingPoint": "粤菜馆的沸腾美学，黄牛肉片薄如纸铺底，滚油浇淋瞬间沸腾，辣椒花椒在油中翻涌，视觉与味觉双重冲击",
          "coreIngredients": "黄牛里脊肉、干辣椒段、花椒、郫县豆瓣酱、蒜蓉、姜片、豆芽、生菜（贵州关岭黄牛、四川汉源花椒、郫县豆瓣酱）",
          "cookingTechnique": "[高] 牛肉逆纹切薄片→蛋清淀粉上浆→豆芽生菜焯水垫底→牛肉片滑油铺于菜上→锅中宽油烧至七成热→下干辣椒花椒爆香→滚油连辣椒浇淋牛肉→嗞啦沸腾即成（粉红牛肉薄片→上浆后略带乳白→滑油后变白嫩→铺底待浇→滚油浇淋瞬间沸腾→辣椒花椒在油中炸开→成品红油翻涌）",
          "tasteProfile": "麻辣滚烫、肉嫩滑爽、油香浓郁、层次分明，配:郫县豆瓣酱、干辣椒段、花椒、蒜蓉",
          "closeupFeature": "牛肉片薄嫩粉红铺陈，表面覆盖红亮辣油，干辣椒段与花椒粒嵌于油中，油面沸腾冒泡嗞嗞作响，蒜蓉姜片点缀",
          "mediumFeature": "厨师手持铁勺将滚油浇淋而下，油面瞬间沸腾翻涌，辣椒花椒在油中旋转跳跃，白烟升腾，视觉冲击强烈",
          "fullFeature": "大号白瓷深盆中红油沸腾，牛肉隐于红亮油面之下，干辣椒密布如火山岩浆，配以木勺与白饭，气势磅礴",
          "colorTexture": "红亮油面如熔岩，牛肉粉嫩隐现，干辣椒深红，花椒棕褐，油光沸腾",
          "cameraSetup": "Canon R5 C + RF 100mm f/2.8L Macro IS",
          "colorTone": "烧腊暖金",
          "bestAngle": "皮肉切面",
          "thumbnailFrame": "沸腾黄牛肉，皮肉切面特写，烧腊暖金色调，极浅景深，背景全暗，左上45度侧光，牛肉片薄嫩粉红铺陈，表面覆盖红亮辣油，干，蒸汽/油光粒子，9:16竖屏构图，极致特写，无人物出镜，无文字叠加"
        }
      }
    },
    {
      "id": "dish:huangfeihong-zhangzhongbao",
      "type": "service",
      "name": "黄飞鸿掌中宝",
      "summary": "湘遇川味 川湘荟萃·黄飞鸿掌中宝",
      "tags": [
        "湘遇川味",
        "川湘菜",
        "黄飞鸿掌中宝"
      ],
      "complexity": "moderate",
      "metadata": {
        "dishProfile": {
          "name": "黄飞鸿掌中宝",
          "cuisineCategory": "川湘菜",
          "coreSellingPoint": "鸡膝软骨酥炸至金黄，配以黄飞鸿麻辣花生同炒，一口嘎嘣脆，麻辣鲜香满口生风，佐酒绝配",
          "coreIngredients": "鸡膝软骨（掌中宝）、黄飞鸿麻辣花生、干辣椒节、花椒、青红椒粒、酥炸粉（清远走地鸡膝软骨、四川麻辣花生）",
          "cookingTechnique": "[中] 掌中宝清洗沥干→盐料酒腌制→裹酥炸粉→宽油炸至金黄酥脆→锅留底油爆香辣椒花椒→下掌中宝与麻辣花生翻炒→撒青红椒粒出锅（乳白掌中宝→腌制后略带酱色→裹粉后白粉覆盖→油炸至金黄酥脆鼓起→翻炒后挂满辣椒碎与花生衣）",
          "tasteProfile": "酥脆麻辣、嘎嘣作响、花生浓香、越嚼越香，配:干辣椒节、花椒、麻辣花生自带调味",
          "closeupFeature": "掌中宝金黄圆鼓，表面酥粉颗粒分明，麻辣花生红衣半脱嵌于其间，干辣椒节深红，青红椒粒点缀，整体干爽不油腻",
          "mediumFeature": "漏勺中炸好的掌中宝金黄诱人，铁锅中与辣椒花生翻飞，酥脆声清晰可闻，花生红衣在翻炒中微微脱落",
          "fullFeature": "长方形木板上白纸铺底，掌中宝与麻辣花生堆叠如山，配以冰镇啤酒杯与竹筷，休闲佐酒氛围",
          "colorTexture": "金黄酥脆主体，麻辣花生棕红，干辣椒深红，青红椒翠绿点缀，干爽颗粒感",
          "cameraSetup": "Canon R5 C + RF 100mm f/2.8L Macro IS",
          "colorTone": "烧腊暖金",
          "bestAngle": "皮肉切面",
          "thumbnailFrame": "黄飞鸿掌中宝，皮肉切面特写，烧腊暖金色调，极浅景深，背景全暗，左上45度侧光，掌中宝金黄圆鼓，表面酥粉颗粒分明，麻辣花，蒸汽/油光粒子，9:16竖屏构图，极致特写，无人物出镜，无文字叠加"
        }
      }
    },
    {
      "id": "dish:xianla-duojiao-zheng-dayutou",
      "type": "service",
      "name": "鲜辣剁椒蒸大鱼头",
      "summary": "湘遇川味 川湘荟萃·鲜辣剁椒蒸大鱼头",
      "tags": [
        "湘遇川味",
        "川湘菜",
        "鲜辣剁椒蒸大鱼头"
      ],
      "complexity": "moderate",
      "metadata": {
        "dishProfile": {
          "name": "鲜辣剁椒蒸大鱼头",
          "cuisineCategory": "川湘菜",
          "coreSellingPoint": "千岛湖有机鳙鱼头，湖南秘制剁椒铺满鱼面，猛火蒸出鲜辣交融，鱼脑嫩滑如豆腐，剁椒鲜香入骨三分",
          "coreIngredients": "千岛湖有机鳙鱼（8斤以上）、湖南湘潭秘制剁椒",
          "cookingTechnique": "[中] 鱼头劈开去鳃洗净→料酒姜片腌制去腥→盘底铺姜片→鱼头皮朝上摆盘→铺满剁椒姜蒜末→猛火蒸12分钟→出锅淋蒸鱼豉油→撒葱花浇热油（银白鱼头→腌制后略带酒香→铺剁椒后红白分明→蒸制中鱼眼变白凸起→蒸熟后鱼皮开裂鱼脑嫩白→浇油后嗞嗞作响油光闪亮）",
          "tasteProfile": "鲜辣浓烈、鱼脑嫩滑、剁椒酸香、回味甘甜，配:蒸鱼豉油、剁椒自带酸香、热油激香葱花",
          "closeupFeature": "鱼头硕大，鱼眼微凸，表面铺满鲜红剁椒粒，姜蒜末嵌于剁椒之间，鱼皮光泽油亮，蒸汁沿鱼身流淌，葱花散落",
          "mediumFeature": "蒸笼揭盖瞬间白气升腾，鱼头在蒸气中若隐若现，鲜红剁椒铺满鱼面如红毯，热油浇淋葱花嗞嗞作响",
          "fullFeature": "大号椭圆白瓷盘中鱼头占满盘面，鲜红剁椒覆盖如火山，配以青花小碗盛蒸汁，白饭与竹筷，气势恢宏",
          "colorTexture": "鲜红剁椒铺面，鱼皮银白油亮，鱼脑乳白嫩滑，蒸汁金黄清亮",
          "cameraSetup": "ARRI Alexa Mini LF + Zeiss Supreme Prime",
          "colorTone": "清蒸冷白",
          "bestAngle": "蒸汽揭盖",
          "thumbnailFrame": "鲜辣剁椒蒸大鱼头，蒸汽揭盖瞬间，清蒸冷白色调，极浅景深，背景全暗，左上45度侧光，鱼头硕大，鱼眼微凸，表面铺满鲜红剁椒粒，，蒸汽/油光粒子，9:16竖屏构图，极致特写，无人物出镜，无文字叠加"
        }
      }
    },
    {
      "id": "dish:chuanxiang-majiao-niuxiaopai",
      "type": "service",
      "name": "川香麻椒牛小排",
      "summary": "湘遇川味 川湘荟萃·川香麻椒牛小排",
      "tags": [
        "湘遇川味",
        "川湘菜",
        "川香麻椒牛小排"
      ],
      "complexity": "moderate",
      "metadata": {
        "dishProfile": {
          "name": "川香麻椒牛小排",
          "cuisineCategory": "川湘菜",
          "coreSellingPoint": "澳洲M5和牛小排先煎后焖，青麻椒与红花椒双椒合击，麻感层层递进，牛肉入口即化又麻得通透",
          "coreIngredients": "澳洲M5和牛小排、青麻椒、红花椒、干辣椒、姜片、蒜瓣、八角、桂皮（澳洲M5和牛小排、四川金阳青麻椒、汉源红花椒）",
          "cookingTechnique": "[高] 牛小排切寸段→平底锅煎至两面焦香→砂锅底铺姜蒜八角桂皮→放入煎好牛小排→加水没过→大火烧开转小火焖60分钟→收汁后撒双椒粉→热油激香（鲜红牛小排→煎制后两面焦褐→焖煮中肉色变深软烂→收汁后挂满浓酱→撒椒粉后青红点缀→热油激香后油光四溢）",
          "tasteProfile": "麻香浓郁、肉烂骨酥、层次递进、回甘悠长，配:八角桂皮卤汁、青麻椒粉、红花椒粉",
          "closeupFeature": "牛小排骨肉微离，肉面深褐油亮，青麻椒碎粒与红花椒嵌于肉缝，肉纹清晰可见，骨端露出白骨，油光闪烁",
          "mediumFeature": "砂锅中牛小排焖煮至汤汁浓稠，筷子轻夹骨肉即离，撒下麻椒粉瞬间热油激香，白烟带着麻香升腾",
          "fullFeature": "黑陶砂锅中牛小排层层叠放，浓汁裹肉油亮，青红花椒点缀其间，配以白瓷勺与米饭，暖色调氛围",
          "colorTexture": "深褐酱色肉面，骨端乳白，青麻椒翠绿，红花椒棕红，油润浓稠",
          "cameraSetup": "Canon R5 C + RF 100mm f/2.8L Macro IS",
          "colorTone": "烧腊暖金",
          "bestAngle": "皮肉切面",
          "thumbnailFrame": "川香麻椒牛小排，皮肉切面特写，烧腊暖金色调，极浅景深，背景全暗，左上45度侧光，牛小排骨肉微离，肉面深褐油亮，青麻椒碎粒，蒸汽/油光粒子，9:16竖屏构图，极致特写，无人物出镜，无文字叠加"
        }
      }
    },
    {
      "id": "dish:gangguo-feichang-wang",
      "type": "service",
      "name": "干锅肥肠王",
      "summary": "湘遇川味 川湘荟萃·干锅肥肠王",
      "tags": [
        "湘遇川味",
        "川湘菜",
        "干锅肥肠王"
      ],
      "complexity": "moderate",
      "metadata": {
        "dishProfile": {
          "name": "干锅肥肠王",
          "cuisineCategory": "川湘菜",
          "coreSellingPoint": "肥肠反复清洗去腥，先卤后炸再干锅焖，外皮焦脆内里软糯，干锅持续加热越吃越香，下饭下酒两相宜",
          "coreIngredients": "猪肥肠、洋葱、青红椒、干辣椒、花椒、蒜子、姜片、豆瓣酱、白芝麻（精选猪肥肠、郫县豆瓣酱、四川干辣椒）",
          "cookingTechnique": "[高] 肥肠翻面去油膜→面粉白醋反复搓洗→焯水去腥→秘制卤水卤60分钟→切滚刀块→宽油炸至表皮起泡→干锅底铺洋葱→下肥肠辣椒翻炒→小火持续加热（乳白肥肠→焯水后紧缩→卤制后酱褐软烂→油炸后表皮起泡焦脆→干锅翻炒后挂满酱料→持续加热中越炒越香）",
          "tasteProfile": "焦香麻辣、外脆内糯、越嚼越香、回味悠长，配:豆瓣酱、干辣椒、花椒、洋葱垫底出汁",
          "closeupFeature": "肥肠滚刀块表皮起泡焦脆，内壁乳白软糯，干辣椒与花椒嵌于褶皱之间，洋葱丝半透明，白芝麻散落，油光微亮",
          "mediumFeature": "干锅中小火持续加热，肥肠在锅中嗞嗞作响，洋葱丝渐变透明出香，辣椒花椒在油中微微翻动，热气蒸腾",
          "fullFeature": "铜质干锅架于酒精炉上，肥肠堆叠冒尖，洋葱铺底，青红椒点缀，配以竹筷与冰啤酒，热闹聚餐氛围",
          "colorTexture": "焦褐起泡表皮，乳白内壁，洋葱半透明，辣椒深红，整体油润干香",
          "cameraSetup": "Canon R5 C + RF 100mm f/2.8L Macro IS",
          "colorTone": "烧腊暖金",
          "bestAngle": "皮肉切面",
          "thumbnailFrame": "干锅肥肠王，皮肉切面特写，烧腊暖金色调，极浅景深，背景全暗，左上45度侧光，肥肠滚刀块表皮起泡焦脆，内壁乳白软糯，干，蒸汽/油光粒子，9:16竖屏构图，极致特写，无人物出镜，无文字叠加"
        }
      }
    },
    {
      "id": "dish:chuanxiang-huiguo-rou",
      "type": "service",
      "name": "川香回锅肉",
      "summary": "湘遇川味 川湘荟萃·川香回锅肉",
      "tags": [
        "湘遇川味",
        "川湘菜",
        "川香回锅肉"
      ],
      "complexity": "moderate",
      "metadata": {
        "dishProfile": {
          "name": "川香回锅肉",
          "cuisineCategory": "川湘菜",
          "coreSellingPoint": "粤菜馆的回锅肉坚持二刀肉先煮后煎再炒，肉片薄如灯影透光，郫县豆瓣炒出红油，蒜苗断生翠绿，川菜之王当之无愧",
          "coreIngredients": "猪二刀肉（后臀尖）、郫县豆瓣酱、甜面酱、蒜苗、青红椒、姜片、料酒（精选猪二刀肉、郫县陈年豆瓣酱、四川甜面酱）",
          "cookingTechnique": "[中] 二刀肉整块冷水下锅→加姜料酒煮至八成熟→捞出晾凉切薄片→无油干锅煎至肉片卷曲出油→拨一边下豆瓣酱炒出红油→加甜面酱→下蒜苗青红椒翻炒→大火收汁（粉白二刀肉→煮后灰白紧实→晾凉切薄片→干煎后卷曲出油肥肉变透明→豆瓣酱炒出红油→蒜苗翻炒后翠绿断生→成品油亮酱红）",
          "tasteProfile": "酱香浓郁、微辣回甜、肥肉焦香、蒜苗清鲜，配:郫县豆瓣酱、甜面酱、蒜苗自带清香",
          "closeupFeature": "肉片薄而卷曲如灯盏，肥肉部分透明泛金光，瘦肉深褐入味，红油均匀裹附，蒜苗翠绿挺立，豆瓣碎粒可见",
          "mediumFeature": "铁锅中肉片煎至卷曲出油，豆瓣酱下锅瞬间红油翻涌，蒜苗入锅翻炒翠绿与红油交织，锅气升腾",
          "fullFeature": "白瓷深盘中肉片层层叠叠如花瓣绽放，红油浸润，蒜苗青翠穿插其间，配以白米饭与汤碗，家常美味",
          "colorTexture": "红油酱色裹肉，肥肉透明金黄，瘦肉深褐，蒜苗翠绿，油润发亮",
          "cameraSetup": "Canon R5 C + RF 100mm f/2.8L Macro IS",
          "colorTone": "烧腊暖金",
          "bestAngle": "皮肉切面",
          "thumbnailFrame": "川香回锅肉，皮肉切面特写，烧腊暖金色调，极浅景深，背景全暗，左上45度侧光，肉片薄而卷曲如灯盏，肥肉部分透明泛金光，，蒸汽/油光粒子，9:16竖屏构图，极致特写，无人物出镜，无文字叠加"
        }
      }
    }
  ]
}
